{"type":"script","seleniumVersion":"2","formatVersion":2,"steps":[{"type":"get","url":"http://dev.vetmedical.ru"},{"type":"waitForElementPresent","locator":{"type":"css selector","value":"#sign_in"}},{"type":"clickElement","locator":{"type":"css selector","value":"#sign_in"}},{"type":"waitForElementPresent","locator":{"type":"css selector","value":"#ips_username"}},{"type":"setElementText","locator":{"type":"css selector","value":"#ips_username"},"text":"AlexanderSW"},{"type":"waitForElementPresent","locator":{"type":"css selector","value":"#ips_password"}},{"type":"setElementText","locator":{"type":"css selector","value":"#ips_password"},"text":"210785ap"},{"type":"waitForElementPresent","locator":{"type":"css selector","value":"#b-login__submit-form"}},{"type":"clickElement","locator":{"type":"css selector","value":"#b-login__submit-form"}},{"type":"pause","waitTime":"5000"},{"type":"waitForElementPresent","locator":{"type":"css selector","value":"#regstepwise_upload_document_submit"}},{"type":"clickElement","locator":{"type":"css selector","value":"#regstepwise_upload_document_submit"}},{"type":"waitForElementPresent","locator":{"type":"css selector","value":"input[name=\"FILE_UPLOAD\"]"}},{"type":"setElementText","locator":{"type":"css selector","value":"input[name=\"FILE_UPLOAD\"]"},"text":"E:\\Фильмы\\аварари спешал фор ю (чясть3)\\JPG-PNG\\nikon___free_icon__by_ifyouplease"},{"type":"waitForElementPresent","locator":{"type":"css selector","value":"#registration_form > div > div.b-registration-step__header > div"}},{"type":"assertText","locator":{"type":"css selector","value":"#registration_form > div > div.b-registration-step__header > div"},"text":"*Вы успешно зарегистрировались!*","negated":false},{"type":"waitForElementPresent","locator":{"type":"css selector","value":"#regstepwise_close_button"}},{"type":"clickElement","locator":{"type":"css selector","value":"#regstepwise_close_button"}}]}