{"type":"script","seleniumVersion":"2","formatVersion":2,"steps":[{"type":"get","url":"http://dev.vetmedical.ru/"},{"type":"waitForElementPresent","locator":{"type":"css selector","value":"#sign_in"}},{"type":"clickElement","locator":{"type":"css selector","value":"#sign_in"}},{"type":"waitForElementPresent","locator":{"type":"css selector","value":"#login_popup > div.b-login-form__forget-passwrod > a"}},{"type":"clickElement","locator":{"type":"css selector","value":"#login_popup > div.b-login-form__forget-passwrod > a"}},{"type":"waitForElementPresent","locator":{"type":"css selector","value":"#email_addy"}},{"type":"setElementText","locator":{"type":"css selector","value":"#email_addy"},"text":"rabotasw@gmail.com"},{"type":"waitForElementPresent","locator":{"type":"css selector","value":"#lost_pass_form > fieldset > input"}},{"type":"clickElement","locator":{"type":"css selector","value":"#lost_pass_form > fieldset > input"}},{"type":"waitForElementPresent","locator":{"type":"css selector","value":"#main > div > p"}},{"type":"assertText","locator":{"type":"css selector","value":"#main > div > p"},"text":"*Вам отправлено письмо с информацией о дальнейших действиях. Вы получите его в течение 10 минут или раньше.*","negated":false}]}