{"type":"script","seleniumVersion":"2","formatVersion":2,"steps":[{"type":"get","url":"http://www.fiberscope.net/es/"},{"type":"waitForElementPresent","locator":{"type":"css selector","value":"a[href*=\"/es/drain-camera-gecko-3000-s.html\"] > .b-main-category-list__item-wrapper > h3.b-main-category-list__item-title > span"}},{"type":"clickElement","locator":{"type":"css selector","value":"a[href*=\"/es/drain-camera-gecko-3000-s.html\"] > .b-main-category-list__item-wrapper > h3.b-main-category-list__item-title > span"}},{"type":"waitForElementPresent","locator":{"type":"css selector","value":"link[rel=\"canonical\"][href=\"http://www.fiberscope.net/es/drain-camera-gecko-3000-s.html\"]"}},{"type":"assertElementPresent","locator":{"type":"css selector","value":"link[rel=\"canonical\"][href=\"http://www.fiberscope.net/es/drain-camera-gecko-3000-s.html\"]"},"negated":false},{"type":"waitForElementPresent","locator":{"type":"css selector","value":"link[rel=\"alternate\"][media=\"only screen and (max-width: 640px)\"][href=\"http://m.fiberscope.net/es/drain-camera-gecko-3000-s.html\"]"}},{"type":"assertElementPresent","locator":{"type":"css selector","value":"link[rel=\"alternate\"][media=\"only screen and (max-width: 640px)\"][href=\"http://m.fiberscope.net/es/drain-camera-gecko-3000-s.html\"]"},"negated":false},{"type":"waitForElementPresent","locator":{"type":"css selector","value":"link[rel=\"alternate\"][hreflang=\"x-default\"][href=\"http://www.fiberscope.net/drain-camera-gecko-3000-s.html\"]"}},{"type":"assertElementPresent","locator":{"type":"css selector","value":"link[rel=\"alternate\"][hreflang=\"x-default\"][href=\"http://www.fiberscope.net/drain-camera-gecko-3000-s.html\"]"},"negated":false},{"type":"waitForElementPresent","locator":{"type":"css selector","value":"link[rel=\"alternate\"][hreflang=\"en-CA\"][href=\"http://www.fiberscope.net/ca/drain-camera-gecko-3000-s.html\"]"}},{"type":"assertElementPresent","locator":{"type":"css selector","value":"link[rel=\"alternate\"][hreflang=\"en-CA\"][href=\"http://www.fiberscope.net/ca/drain-camera-gecko-3000-s.html\"]"},"negated":false},{"type":"waitForElementPresent","locator":{"type":"css selector","value":"link[rel=\"alternate\"][hreflang=\"es\"][href=\"http://www.fiberscope.net/es/drain-camera-gecko-3000-s.html\"]"}},{"type":"assertElementPresent","locator":{"type":"css selector","value":"link[rel=\"alternate\"][hreflang=\"es\"][href=\"http://www.fiberscope.net/es/drain-camera-gecko-3000-s.html\"]"},"negated":false},{"type":"waitForElementPresent","locator":{"type":"css selector","value":"link[rel=\"alternate\"][hreflang=\"ru\"][href=\"http://www.fiberscope.net/ru/drain-camera-gecko-3000-s.html\"]"}},{"type":"assertElementPresent","locator":{"type":"css selector","value":"link[rel=\"alternate\"][hreflang=\"ru\"][href=\"http://www.fiberscope.net/ru/drain-camera-gecko-3000-s.html\"]"},"negated":false},{"type":"waitForElementPresent","locator":{"type":"css selector","value":".b-menu__list > .b-menu__item:nth-of-type(1) > a[href*=\"/es/\"] > span"}},{"type":"clickElement","locator":{"type":"css selector","value":".b-menu__list > .b-menu__item:nth-of-type(1) > a[href*=\"/es/\"] > span"}},{"type":"waitForElementPresent","locator":{"type":"css selector","value":"a[href*=\"/es/video-borescopes-video-scopes.html\"] > .ts-1"}},{"type":"clickElement","locator":{"type":"css selector","value":"a[href*=\"/es/video-borescopes-video-scopes.html\"] > .ts-1"}},{"type":"waitForElementPresent","locator":{"type":"css selector","value":"a[href*=\"/es/orion-video-borescope.html\"] > h2.b-product-catalog__item-title"}},{"type":"clickElement","locator":{"type":"css selector","value":"a[href*=\"/es/orion-video-borescope.html\"] > h2.b-product-catalog__item-title"}},{"type":"waitForElementPresent","locator":{"type":"css selector","value":"link[rel=\"canonical\"][href=\"http://www.fiberscope.net/es/orion-video-borescope.html\"]"}},{"type":"assertElementPresent","locator":{"type":"css selector","value":"link[rel=\"canonical\"][href=\"http://www.fiberscope.net/es/orion-video-borescope.html\"]"},"negated":false},{"type":"waitForElementPresent","locator":{"type":"css selector","value":"link[rel=\"alternate\"][media=\"only screen and (max-width: 640px)\"][href=\"http://m.fiberscope.net/es/orion-video-borescope.html\"]"}},{"type":"assertElementPresent","locator":{"type":"css selector","value":"link[rel=\"alternate\"][media=\"only screen and (max-width: 640px)\"][href=\"http://m.fiberscope.net/es/orion-video-borescope.html\"]"},"negated":false},{"type":"waitForElementPresent","locator":{"type":"css selector","value":"link[rel=\"alternate\"][hreflang=\"x-default\"][href=\"http://www.fiberscope.net/orion-video-borescope.html\"]"}},{"type":"assertElementPresent","locator":{"type":"css selector","value":"link[rel=\"alternate\"][hreflang=\"x-default\"][href=\"http://www.fiberscope.net/orion-video-borescope.html\"]"},"negated":false},{"type":"waitForElementPresent","locator":{"type":"css selector","value":"link[rel=\"alternate\"][hreflang=\"en-CA\"][href=\"http://www.fiberscope.net/ca/orion-video-borescope.html\"]"}},{"type":"assertElementPresent","locator":{"type":"css selector","value":"link[rel=\"alternate\"][hreflang=\"en-CA\"][href=\"http://www.fiberscope.net/ca/orion-video-borescope.html\"]"},"negated":false},{"type":"waitForElementPresent","locator":{"type":"css selector","value":"link[rel=\"alternate\"][hreflang=\"es\"][href=\"http://www.fiberscope.net/es/orion-video-borescope.html\"]"}},{"type":"assertElementPresent","locator":{"type":"css selector","value":"link[rel=\"alternate\"][hreflang=\"es\"][href=\"http://www.fiberscope.net/es/orion-video-borescope.html\"]"},"negated":false},{"type":"waitForElementPresent","locator":{"type":"css selector","value":"link[rel=\"alternate\"][hreflang=\"ru\"][href=\"http://www.fiberscope.net/ru/orion-video-borescope.html\"]"}},{"type":"assertElementPresent","locator":{"type":"css selector","value":"link[rel=\"alternate\"][hreflang=\"ru\"][href=\"http://www.fiberscope.net/ru/orion-video-borescope.html\"]"},"negated":false},{"type":"waitForElementPresent","locator":{"type":"css selector","value":"a[href*=\"/es/borescope-borescope-light-sources.html\"] > .ts-1"}},{"type":"clickElement","locator":{"type":"css selector","value":"a[href*=\"/es/borescope-borescope-light-sources.html\"] > .ts-1"}},{"type":"waitForElementPresent","locator":{"type":"css selector","value":"a[href*=\"/es/spark-xtr-led-for-borescopes-endoscopes.html\"] > h2.b-product-catalog__item-title"}},{"type":"clickElement","locator":{"type":"css selector","value":"a[href*=\"/es/spark-xtr-led-for-borescopes-endoscopes.html\"] > h2.b-product-catalog__item-title"}},{"type":"waitForElementPresent","locator":{"type":"css selector","value":"link[rel=\"canonical\"][href=\"http://www.fiberscope.net/es/spark-xtr-led-for-borescopes-endoscopes.html\"]"}},{"type":"assertElementPresent","locator":{"type":"css selector","value":"link[rel=\"canonical\"][href=\"http://www.fiberscope.net/es/spark-xtr-led-for-borescopes-endoscopes.html\"]"},"negated":false},{"type":"waitForElementPresent","locator":{"type":"css selector","value":"link[rel=\"alternate\"][media=\"only screen and (max-width: 640px)\"][href=\"http://m.fiberscope.net/es/spark-xtr-led-for-borescopes-endoscopes.html\"]"}},{"type":"assertElementPresent","locator":{"type":"css selector","value":"link[rel=\"alternate\"][media=\"only screen and (max-width: 640px)\"][href=\"http://m.fiberscope.net/es/spark-xtr-led-for-borescopes-endoscopes.html\"]"},"negated":false},{"type":"waitForElementPresent","locator":{"type":"css selector","value":"link[rel=\"alternate\"][hreflang=\"x-default\"][href=\"http://www.fiberscope.net/spark-xtr-led-for-borescopes-endoscopes.html\"]"}},{"type":"assertElementPresent","locator":{"type":"css selector","value":"link[rel=\"alternate\"][hreflang=\"x-default\"][href=\"http://www.fiberscope.net/spark-xtr-led-for-borescopes-endoscopes.html\"]"},"negated":false},{"type":"waitForElementPresent","locator":{"type":"css selector","value":"link[rel=\"alternate\"][hreflang=\"en-CA\"][href=\"http://www.fiberscope.net/ca/spark-xtr-led-for-borescopes-endoscopes.html\"]"}},{"type":"assertElementPresent","locator":{"type":"css selector","value":"link[rel=\"alternate\"][hreflang=\"en-CA\"][href=\"http://www.fiberscope.net/ca/spark-xtr-led-for-borescopes-endoscopes.html\"]"},"negated":false},{"type":"waitForElementPresent","locator":{"type":"css selector","value":"link[rel=\"alternate\"][hreflang=\"es\"][href=\"http://www.fiberscope.net/es/spark-xtr-led-for-borescopes-endoscopes.html\"]"}},{"type":"assertElementPresent","locator":{"type":"css selector","value":"link[rel=\"alternate\"][hreflang=\"es\"][href=\"http://www.fiberscope.net/es/spark-xtr-led-for-borescopes-endoscopes.html\"]"},"negated":false},{"type":"waitForElementPresent","locator":{"type":"css selector","value":"link[rel=\"alternate\"][hreflang=\"ru\"][href=\"http://www.fiberscope.net/ru/spark-xtr-led-for-borescopes-endoscopes.html\"]"}},{"type":"assertElementPresent","locator":{"type":"css selector","value":"link[rel=\"alternate\"][hreflang=\"ru\"][href=\"http://www.fiberscope.net/ru/spark-xtr-led-for-borescopes-endoscopes.html\"]"},"negated":false},{"type":"waitForElementPresent","locator":{"type":"css selector","value":"a[href*=\"/es/borescope-borescope-light-sources.html\"] > .ts-1"}},{"type":"clickElement","locator":{"type":"css selector","value":"a[href*=\"/es/borescope-borescope-light-sources.html\"] > .ts-1"}},{"type":"waitForElementPresent","locator":{"type":"css selector","value":"a[href*=\"/es/fiber-optic-light-guide-cable.html\"] > h2.b-product-catalog__item-title"}},{"type":"clickElement","locator":{"type":"css selector","value":"a[href*=\"/es/fiber-optic-light-guide-cable.html\"] > h2.b-product-catalog__item-title"}},{"type":"waitForElementPresent","locator":{"type":"css selector","value":"link[rel=\"canonical\"][href=\"http://www.fiberscope.net/es/fiber-optic-light-guide-cable.html\"]"}},{"type":"assertElementPresent","locator":{"type":"css selector","value":"link[rel=\"canonical\"][href=\"http://www.fiberscope.net/es/fiber-optic-light-guide-cable.html\"]"},"negated":false},{"type":"waitForElementPresent","locator":{"type":"css selector","value":"link[rel=\"alternate\"][media=\"only screen and (max-width: 640px)\"][href=\"http://m.fiberscope.net/es/fiber-optic-light-guide-cable.html\"]"}},{"type":"assertElementPresent","locator":{"type":"css selector","value":"link[rel=\"alternate\"][media=\"only screen and (max-width: 640px)\"][href=\"http://m.fiberscope.net/es/fiber-optic-light-guide-cable.html\"]"},"negated":false},{"type":"waitForElementPresent","locator":{"type":"css selector","value":"link[rel=\"alternate\"][hreflang=\"x-default\"][href=\"http://www.fiberscope.net/fiber-optic-light-guide-cable.html\"]"}},{"type":"assertElementPresent","locator":{"type":"css selector","value":"link[rel=\"alternate\"][hreflang=\"x-default\"][href=\"http://www.fiberscope.net/fiber-optic-light-guide-cable.html\"]"},"negated":false},{"type":"waitForElementPresent","locator":{"type":"css selector","value":"link[rel=\"alternate\"][hreflang=\"en-CA\"][href=\"http://www.fiberscope.net/ca/fiber-optic-light-guide-cable.html\"]"}},{"type":"assertElementPresent","locator":{"type":"css selector","value":"link[rel=\"alternate\"][hreflang=\"en-CA\"][href=\"http://www.fiberscope.net/ca/fiber-optic-light-guide-cable.html\"]"},"negated":false},{"type":"waitForElementPresent","locator":{"type":"css selector","value":"link[rel=\"alternate\"][hreflang=\"es\"][href=\"http://www.fiberscope.net/es/fiber-optic-light-guide-cable.html\"]"}},{"type":"assertElementPresent","locator":{"type":"css selector","value":"link[rel=\"alternate\"][hreflang=\"es\"][href=\"http://www.fiberscope.net/es/fiber-optic-light-guide-cable.html\"]"},"negated":false},{"type":"waitForElementPresent","locator":{"type":"css selector","value":"link[rel=\"alternate\"][hreflang=\"ru\"][href=\"http://www.fiberscope.net/ru/fiber-optic-light-guide-cable.html\"]"}},{"type":"assertElementPresent","locator":{"type":"css selector","value":"link[rel=\"alternate\"][hreflang=\"ru\"][href=\"http://www.fiberscope.net/ru/fiber-optic-light-guide-cable.html\"]"},"negated":false},{"type":"waitForElementPresent","locator":{"type":"css selector","value":"a[href*=\"/es/borescope-camera.html\"]"}},{"type":"clickElement","locator":{"type":"css selector","value":"a[href*=\"/es/borescope-camera.html\"]"}},{"type":"waitForElementPresent","locator":{"type":"css selector","value":"a[href*=\"/es/video-scope-iris-dvr-x.html\"] > h2.b-product-catalog__item-title"}},{"type":"clickElement","locator":{"type":"css selector","value":"a[href*=\"/es/video-scope-iris-dvr-x.html\"] > h2.b-product-catalog__item-title"}},{"type":"waitForElementPresent","locator":{"type":"css selector","value":"link[rel=\"canonical\"][href=\"http://www.fiberscope.net/es/video-scope-iris-dvr-x.html\"]"}},{"type":"assertElementPresent","locator":{"type":"css selector","value":"link[rel=\"canonical\"][href=\"http://www.fiberscope.net/es/video-scope-iris-dvr-x.html\"]"},"negated":false},{"type":"waitForElementPresent","locator":{"type":"css selector","value":"link[rel=\"alternate\"][media=\"only screen and (max-width: 640px)\"][href=\"http://m.fiberscope.net/es/video-scope-iris-dvr-x.html\"]"}},{"type":"assertElementPresent","locator":{"type":"css selector","value":"link[rel=\"alternate\"][media=\"only screen and (max-width: 640px)\"][href=\"http://m.fiberscope.net/es/video-scope-iris-dvr-x.html\"]"},"negated":false},{"type":"waitForElementPresent","locator":{"type":"css selector","value":"link[rel=\"alternate\"][hreflang=\"x-default\"][href=\"http://www.fiberscope.net/video-scope-iris-dvr-x.html\"]"}},{"type":"assertElementPresent","locator":{"type":"css selector","value":"link[rel=\"alternate\"][hreflang=\"x-default\"][href=\"http://www.fiberscope.net/video-scope-iris-dvr-x.html\"]"},"negated":false},{"type":"waitForElementPresent","locator":{"type":"css selector","value":"link[rel=\"alternate\"][hreflang=\"en-CA\"][href=\"http://www.fiberscope.net/ca/video-scope-iris-dvr-x.html\"]"}},{"type":"assertElementPresent","locator":{"type":"css selector","value":"link[rel=\"alternate\"][hreflang=\"en-CA\"][href=\"http://www.fiberscope.net/ca/video-scope-iris-dvr-x.html\"]"},"negated":false},{"type":"waitForElementPresent","locator":{"type":"css selector","value":"link[rel=\"alternate\"][hreflang=\"es\"][href=\"http://www.fiberscope.net/es/video-scope-iris-dvr-x.html\"]"}},{"type":"assertElementPresent","locator":{"type":"css selector","value":"link[rel=\"alternate\"][hreflang=\"es\"][href=\"http://www.fiberscope.net/es/video-scope-iris-dvr-x.html\"]"},"negated":false},{"type":"waitForElementPresent","locator":{"type":"css selector","value":"link[rel=\"alternate\"][hreflang=\"ru\"][href=\"http://www.fiberscope.net/ru/video-scope-iris-dvr-x.html\"]"}},{"type":"assertElementPresent","locator":{"type":"css selector","value":"link[rel=\"alternate\"][hreflang=\"ru\"][href=\"http://www.fiberscope.net/ru/video-scope-iris-dvr-x.html\"]"},"negated":false},{"type":"waitForElementPresent","locator":{"type":"css selector","value":"a[href=\"/es/snake-camera-sewer-camera-drain-camera-pipe.html\"] > .ts-1"}},{"type":"clickElement","locator":{"type":"css selector","value":"a[href=\"/es/snake-camera-sewer-camera-drain-camera-pipe.html\"] > .ts-1"}},{"type":"waitForElementPresent","locator":{"type":"css selector","value":"a[href*=\"/es/inspection-camera-viper-adv.html\"] > h2.b-product-catalog__item-title"}},{"type":"clickElement","locator":{"type":"css selector","value":"a[href*=\"/es/inspection-camera-viper-adv.html\"] > h2.b-product-catalog__item-title"}},{"type":"waitForElementPresent","locator":{"type":"css selector","value":"link[rel=\"canonical\"][href=\"http://www.fiberscope.net/es/inspection-camera-viper-adv.html\"]"}},{"type":"assertElementPresent","locator":{"type":"css selector","value":"link[rel=\"canonical\"][href=\"http://www.fiberscope.net/es/inspection-camera-viper-adv.html\"]"},"negated":false},{"type":"waitForElementPresent","locator":{"type":"css selector","value":"link[rel=\"alternate\"][media=\"only screen and (max-width: 640px)\"][href=\"http://m.fiberscope.net/es/inspection-camera-viper-adv.html\"]"}},{"type":"assertElementPresent","locator":{"type":"css selector","value":"link[rel=\"alternate\"][media=\"only screen and (max-width: 640px)\"][href=\"http://m.fiberscope.net/es/inspection-camera-viper-adv.html\"]"},"negated":false},{"type":"waitForElementPresent","locator":{"type":"css selector","value":"link[rel=\"alternate\"][hreflang=\"x-default\"][href=\"http://www.fiberscope.net/inspection-camera-viper-adv.html\"]"}},{"type":"assertElementPresent","locator":{"type":"css selector","value":"link[rel=\"alternate\"][hreflang=\"x-default\"][href=\"http://www.fiberscope.net/inspection-camera-viper-adv.html\"]"},"negated":false},{"type":"waitForElementPresent","locator":{"type":"css selector","value":"link[rel=\"alternate\"][hreflang=\"en-CA\"][href=\"http://www.fiberscope.net/ca/inspection-camera-viper-adv.html\"]"}},{"type":"assertElementPresent","locator":{"type":"css selector","value":"link[rel=\"alternate\"][hreflang=\"en-CA\"][href=\"http://www.fiberscope.net/ca/inspection-camera-viper-adv.html\"]"},"negated":false},{"type":"waitForElementPresent","locator":{"type":"css selector","value":"link[rel=\"alternate\"][hreflang=\"es\"][href=\"http://www.fiberscope.net/es/inspection-camera-viper-adv.html\"]"}},{"type":"assertElementPresent","locator":{"type":"css selector","value":"link[rel=\"alternate\"][hreflang=\"es\"][href=\"http://www.fiberscope.net/es/inspection-camera-viper-adv.html\"]"},"negated":false},{"type":"assertElementPresent","locator":{"type":"css selector","value":"link[rel=\"alternate\"][hreflang=\"ru\"][href=\"http://www.fiberscope.net/ru/inspection-camera-viper-adv.html\"]"},"negated":true},{"type":"waitForElementPresent","locator":{"type":"css selector","value":"a[href=\"/es/snake-camera-sewer-camera-drain-camera-pipe.html\"]"}},{"type":"clickElement","locator":{"type":"css selector","value":"a[href=\"/es/snake-camera-sewer-camera-drain-camera-pipe.html\"]"}},{"type":"waitForElementPresent","locator":{"type":"css selector","value":"a[href*=\"/es/industrial-pipe-inspection-camera-push-rod-camera.html\"] > h2.b-product-catalog__item-title"}},{"type":"clickElement","locator":{"type":"css selector","value":"a[href*=\"/es/industrial-pipe-inspection-camera-push-rod-camera.html\"] > h2.b-product-catalog__item-title"}},{"type":"waitForElementPresent","locator":{"type":"css selector","value":"link[rel=\"canonical\"][href=\"http://www.fiberscope.net/es/industrial-pipe-inspection-camera-push-rod-camera.html\"]"}},{"type":"assertElementPresent","locator":{"type":"css selector","value":"link[rel=\"canonical\"][href=\"http://www.fiberscope.net/es/industrial-pipe-inspection-camera-push-rod-camera.html\"]"},"negated":false},{"type":"waitForElementPresent","locator":{"type":"css selector","value":"link[rel=\"alternate\"][media=\"only screen and (max-width: 640px)\"][href=\"http://m.fiberscope.net/es/industrial-pipe-inspection-camera-push-rod-camera.html\"]"}},{"type":"assertElementPresent","locator":{"type":"css selector","value":"link[rel=\"alternate\"][media=\"only screen and (max-width: 640px)\"][href=\"http://m.fiberscope.net/es/industrial-pipe-inspection-camera-push-rod-camera.html\"]"},"negated":false},{"type":"waitForElementPresent","locator":{"type":"css selector","value":"link[rel=\"alternate\"][hreflang=\"x-default\"][href=\"http://www.fiberscope.net/industrial-pipe-inspection-camera-push-rod-camera.html\"]"}},{"type":"assertElementPresent","locator":{"type":"css selector","value":"link[rel=\"alternate\"][hreflang=\"x-default\"][href=\"http://www.fiberscope.net/industrial-pipe-inspection-camera-push-rod-camera.html\"]"},"negated":false},{"type":"waitForElementPresent","locator":{"type":"css selector","value":"link[rel=\"alternate\"][hreflang=\"en-CA\"][href=\"http://www.fiberscope.net/ca/industrial-pipe-inspection-camera-push-rod-camera.html\"]"}},{"type":"assertElementPresent","locator":{"type":"css selector","value":"link[rel=\"alternate\"][hreflang=\"en-CA\"][href=\"http://www.fiberscope.net/ca/industrial-pipe-inspection-camera-push-rod-camera.html\"]"},"negated":false},{"type":"waitForElementPresent","locator":{"type":"css selector","value":"link[rel=\"alternate\"][hreflang=\"es\"][href=\"http://www.fiberscope.net/es/industrial-pipe-inspection-camera-push-rod-camera.html\"]"}},{"type":"assertElementPresent","locator":{"type":"css selector","value":"link[rel=\"alternate\"][hreflang=\"es\"][href=\"http://www.fiberscope.net/es/industrial-pipe-inspection-camera-push-rod-camera.html\"]"},"negated":false},{"type":"waitForElementPresent","locator":{"type":"css selector","value":"link[rel=\"alternate\"][hreflang=\"ru\"][href=\"http://www.fiberscope.net/ru/industrial-pipe-inspection-camera-push-rod-camera.html\"]"}},{"type":"assertElementPresent","locator":{"type":"css selector","value":"link[rel=\"alternate\"][hreflang=\"ru\"][href=\"http://www.fiberscope.net/ru/industrial-pipe-inspection-camera-push-rod-camera.html\"]"},"negated":false}]}