{"type":"script","seleniumVersion":"2","formatVersion":2,"steps":[{"type":"get","url":"http://www.fiberscope.net/ru/"},{"type":"get","url":"http://www.fiberscope.net/ru/iseries-2-and-4-way-articulating-video-borescope.html"},{"type":"waitForElementPresent","locator":{"type":"css selector","value":"link[rel=\"canonical\"][href=\"http://www.fiberscope.net/ru/iseries-2-and-4-way-articulating-video-borescope.html\"]"}},{"type":"verifyElementPresent","locator":{"type":"css selector","value":"link[rel=\"canonical\"][href=\"http://www.fiberscope.net/ru/iseries-2-and-4-way-articulating-video-borescope.html\"]"},"negated":false},{"type":"waitForElementPresent","locator":{"type":"css selector","value":"link[rel=\"alternate\"][media=\"only screen and (max-width: 640px)\"][href=\"http://m.fiberscope.net/ru/iseries-2-and-4-way-articulating-video-borescope.html\"]"}},{"type":"verifyElementPresent","locator":{"type":"css selector","value":"link[rel=\"alternate\"][media=\"only screen and (max-width: 640px)\"][href=\"http://m.fiberscope.net/ru/iseries-2-and-4-way-articulating-video-borescope.html\"]"},"negated":false},{"type":"waitForElementPresent","locator":{"type":"css selector","value":"link[rel=\"alternate\"][hreflang=\"x-default\"][href=\"http://www.fiberscope.net/iseries-2-and-4-way-articulating-video-borescope.html\"]"}},{"type":"verifyElementPresent","locator":{"type":"css selector","value":"link[rel=\"alternate\"][hreflang=\"x-default\"][href=\"http://www.fiberscope.net/iseries-2-and-4-way-articulating-video-borescope.html\"]"},"negated":false},{"type":"waitForElementPresent","locator":{"type":"css selector","value":"link[rel=\"alternate\"][hreflang=\"en-CA\"][href=\"http://www.fiberscope.net/ca/iseries-2-and-4-way-articulating-video-borescope.html\"]"}},{"type":"verifyElementPresent","locator":{"type":"css selector","value":"link[rel=\"alternate\"][hreflang=\"en-CA\"][href=\"http://www.fiberscope.net/ca/iseries-2-and-4-way-articulating-video-borescope.html\"]"},"negated":false},{"type":"waitForElementPresent","locator":{"type":"css selector","value":"link[rel=\"alternate\"][hreflang=\"ru\"][href=\"http://www.fiberscope.net/ru/iseries-2-and-4-way-articulating-video-borescope.html\"]"}},{"type":"verifyElementPresent","locator":{"type":"css selector","value":"link[rel=\"alternate\"][hreflang=\"ru\"][href=\"http://www.fiberscope.net/ru/iseries-2-and-4-way-articulating-video-borescope.html\"]"},"negated":false},{"type":"verifyElementPresent","locator":{"type":"css selector","value":"link[rel=\"alternate\"][hreflang=\"es\"][href=\"http://www.fiberscope.net/es/iseries-2-and-4-way-articulating-video-borescope.html\"]"},"negated":true},{"type":"get","url":"http://www.fiberscope.net/ru/orion-video-borescope.html"},{"type":"waitForElementPresent","locator":{"type":"css selector","value":"link[rel=\"canonical\"][href=\"http://www.fiberscope.net/ru/orion-video-borescope.html\"]"}},{"type":"verifyElementPresent","locator":{"type":"css selector","value":"link[rel=\"canonical\"][href=\"http://www.fiberscope.net/ru/orion-video-borescope.html\"]"},"negated":false},{"type":"waitForElementPresent","locator":{"type":"css selector","value":"link[rel=\"alternate\"][media=\"only screen and (max-width: 640px)\"][href=\"http://m.fiberscope.net/ru/orion-video-borescope.html\"]"}},{"type":"verifyElementPresent","locator":{"type":"css selector","value":"link[rel=\"alternate\"][media=\"only screen and (max-width: 640px)\"][href=\"http://m.fiberscope.net/ru/orion-video-borescope.html\"]"},"negated":false},{"type":"waitForElementPresent","locator":{"type":"css selector","value":"link[rel=\"alternate\"][hreflang=\"x-default\"][href=\"http://www.fiberscope.net/orion-video-borescope.html\"]"}},{"type":"verifyElementPresent","locator":{"type":"css selector","value":"link[rel=\"alternate\"][hreflang=\"x-default\"][href=\"http://www.fiberscope.net/orion-video-borescope.html\"]"},"negated":false},{"type":"waitForElementPresent","locator":{"type":"css selector","value":"link[rel=\"alternate\"][hreflang=\"en-CA\"][href=\"http://www.fiberscope.net/ca/orion-video-borescope.html\"]"}},{"type":"verifyElementPresent","locator":{"type":"css selector","value":"link[rel=\"alternate\"][hreflang=\"en-CA\"][href=\"http://www.fiberscope.net/ca/orion-video-borescope.html\"]"},"negated":false},{"type":"waitForElementPresent","locator":{"type":"css selector","value":"link[rel=\"alternate\"][hreflang=\"es\"][href=\"http://www.fiberscope.net/es/orion-video-borescope.html\"]"}},{"type":"verifyElementPresent","locator":{"type":"css selector","value":"link[rel=\"alternate\"][hreflang=\"es\"][href=\"http://www.fiberscope.net/es/orion-video-borescope.html\"]"},"negated":false},{"type":"waitForElementPresent","locator":{"type":"css selector","value":"link[rel=\"alternate\"][hreflang=\"ru\"][href=\"http://www.fiberscope.net/ru/orion-video-borescope.html\"]"}},{"type":"verifyElementPresent","locator":{"type":"css selector","value":"link[rel=\"alternate\"][hreflang=\"ru\"][href=\"http://www.fiberscope.net/ru/orion-video-borescope.html\"]"},"negated":false},{"type":"get","url":"http://www.fiberscope.net/ru/iphone-borescope-adapter.html"},{"type":"waitForElementPresent","locator":{"type":"css selector","value":"link[rel=\"canonical\"][href=\"http://www.fiberscope.net/ru/iphone-borescope-adapter.html\"]"}},{"type":"verifyElementPresent","locator":{"type":"css selector","value":"link[rel=\"canonical\"][href=\"http://www.fiberscope.net/ru/iphone-borescope-adapter.html\"]"},"negated":false},{"type":"waitForElementPresent","locator":{"type":"css selector","value":"link[rel=\"alternate\"][media=\"only screen and (max-width: 640px)\"][href=\"http://m.fiberscope.net/ru/iphone-borescope-adapter.html\"]"}},{"type":"verifyElementPresent","locator":{"type":"css selector","value":"link[rel=\"alternate\"][media=\"only screen and (max-width: 640px)\"][href=\"http://m.fiberscope.net/ru/iphone-borescope-adapter.html\"]"},"negated":false},{"type":"waitForElementPresent","locator":{"type":"css selector","value":"link[rel=\"alternate\"][hreflang=\"x-default\"][href=\"http://www.fiberscope.net/iphone-borescope-adapter.html\"]"}},{"type":"verifyElementPresent","locator":{"type":"css selector","value":"link[rel=\"alternate\"][hreflang=\"x-default\"][href=\"http://www.fiberscope.net/iphone-borescope-adapter.html\"]"},"negated":false},{"type":"waitForElementPresent","locator":{"type":"css selector","value":"link[rel=\"alternate\"][hreflang=\"en-CA\"][href=\"http://www.fiberscope.net/ca/iphone-borescope-adapter.html\"]"}},{"type":"verifyElementPresent","locator":{"type":"css selector","value":"link[rel=\"alternate\"][hreflang=\"en-CA\"][href=\"http://www.fiberscope.net/ca/iphone-borescope-adapter.html\"]"},"negated":false},{"type":"waitForElementPresent","locator":{"type":"css selector","value":"link[rel=\"alternate\"][hreflang=\"ru\"][href=\"http://www.fiberscope.net/ru/iphone-borescope-adapter.html\"]"}},{"type":"verifyElementPresent","locator":{"type":"css selector","value":"link[rel=\"alternate\"][hreflang=\"ru\"][href=\"http://www.fiberscope.net/ru/iphone-borescope-adapter.html\"]"},"negated":false},{"type":"verifyElementPresent","locator":{"type":"css selector","value":"link[rel=\"alternate\"][hreflang=\"es\"][href=\"http://www.fiberscope.net/es/iphone-borescope-adapter.html\"]"},"negated":true},{"type":"get","url":"http://www.fiberscope.net/ru/borescope-camera-ed-cam.html"},{"type":"waitForElementPresent","locator":{"type":"css selector","value":"link[rel=\"canonical\"][href=\"http://www.fiberscope.net/ru/borescope-camera-ed-cam.html\"]"}},{"type":"verifyElementPresent","locator":{"type":"css selector","value":"link[rel=\"canonical\"][href=\"http://www.fiberscope.net/ru/borescope-camera-ed-cam.html\"]"},"negated":false},{"type":"waitForElementPresent","locator":{"type":"css selector","value":"link[rel=\"alternate\"][media=\"only screen and (max-width: 640px)\"][href=\"http://m.fiberscope.net/ru/borescope-camera-ed-cam.html\"]"}},{"type":"verifyElementPresent","locator":{"type":"css selector","value":"link[rel=\"alternate\"][media=\"only screen and (max-width: 640px)\"][href=\"http://m.fiberscope.net/ru/borescope-camera-ed-cam.html\"]"},"negated":false},{"type":"waitForElementPresent","locator":{"type":"css selector","value":"link[rel=\"alternate\"][hreflang=\"x-default\"][href=\"http://www.fiberscope.net/borescope-camera-ed-cam.html\"]"}},{"type":"verifyElementPresent","locator":{"type":"css selector","value":"link[rel=\"alternate\"][hreflang=\"x-default\"][href=\"http://www.fiberscope.net/borescope-camera-ed-cam.html\"]"},"negated":false},{"type":"waitForElementPresent","locator":{"type":"css selector","value":"link[rel=\"alternate\"][hreflang=\"en-CA\"][href=\"http://www.fiberscope.net/ca/borescope-camera-ed-cam.html\"]"}},{"type":"verifyElementPresent","locator":{"type":"css selector","value":"link[rel=\"alternate\"][hreflang=\"en-CA\"][href=\"http://www.fiberscope.net/ca/borescope-camera-ed-cam.html\"]"},"negated":false},{"type":"waitForElementPresent","locator":{"type":"css selector","value":"link[rel=\"alternate\"][hreflang=\"ru\"][href=\"http://www.fiberscope.net/ru/borescope-camera-ed-cam.html\"]"}},{"type":"verifyElementPresent","locator":{"type":"css selector","value":"link[rel=\"alternate\"][hreflang=\"ru\"][href=\"http://www.fiberscope.net/ru/borescope-camera-ed-cam.html\"]"},"negated":false},{"type":"verifyElementPresent","locator":{"type":"css selector","value":"link[rel=\"alternate\"][hreflang=\"es\"][href=\"http://www.fiberscope.net/es/borescope-camera-ed-cam.html\"]"},"negated":true},{"type":"get","url":"http://www.fiberscope.net/ru/zoom-inspection-camera.html"},{"type":"waitForElementPresent","locator":{"type":"css selector","value":"link[rel=\"canonical\"][href=\"http://www.fiberscope.net/ru/zoom-inspection-camera.html\"]"}},{"type":"verifyElementPresent","locator":{"type":"css selector","value":"link[rel=\"canonical\"][href=\"http://www.fiberscope.net/ru/zoom-inspection-camera.html\"]"},"negated":false},{"type":"waitForElementPresent","locator":{"type":"css selector","value":"link[rel=\"alternate\"][media=\"only screen and (max-width: 640px)\"][href=\"http://m.fiberscope.net/ru/zoom-inspection-camera.html\"]"}},{"type":"verifyElementPresent","locator":{"type":"css selector","value":"link[rel=\"alternate\"][media=\"only screen and (max-width: 640px)\"][href=\"http://m.fiberscope.net/ru/zoom-inspection-camera.html\"]"},"negated":false},{"type":"waitForElementPresent","locator":{"type":"css selector","value":"link[rel=\"alternate\"][hreflang=\"x-default\"][href=\"http://www.fiberscope.net/zoom-inspection-camera.html\"]"}},{"type":"verifyElementPresent","locator":{"type":"css selector","value":"link[rel=\"alternate\"][hreflang=\"x-default\"][href=\"http://www.fiberscope.net/zoom-inspection-camera.html\"]"},"negated":false},{"type":"waitForElementPresent","locator":{"type":"css selector","value":"link[rel=\"alternate\"][hreflang=\"en-CA\"][href=\"http://www.fiberscope.net/ca/zoom-inspection-camera.html\"]"}},{"type":"verifyElementPresent","locator":{"type":"css selector","value":"link[rel=\"alternate\"][hreflang=\"en-CA\"][href=\"http://www.fiberscope.net/ca/zoom-inspection-camera.html\"]"},"negated":false},{"type":"waitForElementPresent","locator":{"type":"css selector","value":"link[rel=\"alternate\"][hreflang=\"es\"][href=\"http://www.fiberscope.net/es/zoom-inspection-camera.html\"]"}},{"type":"verifyElementPresent","locator":{"type":"css selector","value":"link[rel=\"alternate\"][hreflang=\"es\"][href=\"http://www.fiberscope.net/es/zoom-inspection-camera.html\"]"},"negated":false},{"type":"waitForElementPresent","locator":{"type":"css selector","value":"link[rel=\"alternate\"][hreflang=\"ru\"][href=\"http://www.fiberscope.net/ru/zoom-inspection-camera.html\"]"}},{"type":"verifyElementPresent","locator":{"type":"css selector","value":"link[rel=\"alternate\"][hreflang=\"ru\"][href=\"http://www.fiberscope.net/ru/zoom-inspection-camera.html\"]"},"negated":false}]}